sqliteclosedhelper/__init__.py
sqliteclosedhelper-1.0.3.dist-info/LICENSE
sqliteclosedhelper-1.0.3.dist-info/METADATA
sqliteclosedhelper-1.0.3.dist-info/WHEEL
sqliteclosedhelper-1.0.3.dist-info/top_level.txt
sqliteclosedhelper-1.0.3.dist-info/RECORD
