Metadata-Version: 2.1
Name: sqliteclosedhelper
Version: 1.0.3
Summary: Sqlite helper module
Home-page: https://github.com/wisdomrider/sqliteclosedhelper-python
Author: wisdomrider
Author-email: avishekzone@gmail.com
License: MIT
Platform: UNKNOWN
Classifier: License :: OSI Approved :: MIT License
Classifier: Programming Language :: Python :: 3
Classifier: Programming Language :: Python :: 3.7
